fence
setup.py
pyfence/__init__.py
pyfence/bootstrap.py
pyfence/compat.py
pyfence/core.py
pyfence/log.py
pyfence.egg-info/PKG-INFO
pyfence.egg-info/SOURCES.txt
pyfence.egg-info/dependency_links.txt
pyfence.egg-info/top_level.txt