Metadata-Version: 1.0
Name: pyfence
Version: 0.1.3
Summary: Automatic type verificator for Python
Home-page: http://eugeny.github.io/pyfence/
Author: Eugene Pankov
Author-email: e@ajenti.org
License: UNKNOWN
Platform: UNKNOWN
